{"analysis": [{"嚴重程度": "(真)嚴重", "是否": "是", "時間": "(衫)(逐)(日)", "特徵1": "無", "特徵2": "無", "症狀": "頭痛"}, {"嚴重程度": "一些嚴重", "是否": "是", "時間": "一個禮拜", "特徵1": "黃色", "特徵2": "的臭", "症狀": "流鼻水"}, {"嚴重程度": "一(點)(仔)嚴重", "是否": "是", "時間": "(衫)四天", "特徵1": "無", "特徵2": "無", "症狀": "鼻竇壓痛"}, {"嚴重程度": "有(足)嚴重(愛)", "是否": "是", "時間": "一個禮拜", "特徵1": "無", "特徵2": "無", "症狀": "鼻塞"}, {"嚴重程度": "有一些嚴重", "是否": "是", "時間": "一個禮拜", "特徵1": "無", "特徵2": "無", "症狀": "口臭"}], "birthday": "1987/08/07", "gender": "男", "id_num": "Q123456789", "name": "王大明", "phone": "0912345678"}